.venv/lib/python3.11/site-packages/_pytest/py.typed
.venv/lib/python3.11/site-packages/asttokens/py.typed
.venv/lib/python3.11/site-packages/click/py.typed
.venv/lib/python3.11/site-packages/devtools/py.typed
.venv/lib/python3.11/site-packages/executing/py.typed
.venv/lib/python3.11/site-packages/filelock/py.typed
.venv/lib/python3.11/site-packages/git/py.typed
.venv/lib/python3.11/site-packages/identify/py.typed
.venv/lib/python3.11/site-packages/iniconfig/py.typed
.venv/lib/python3.11/site-packages/isort/_vendored/tomli/py.typed
.venv/lib/python3.11/site-packages/isort/py.typed
.venv/lib/python3.11/site-packages/jinja2/py.typed
.venv/lib/python3.11/site-packages/markdown_it/py.typed
.venv/lib/python3.11/site-packages/markupsafe/py.typed
.venv/lib/python3.11/site-packages/mdurl/py.typed
.venv/lib/python3.11/site-packages/mypy/py.typed
.venv/lib/python3.11/site-packages/packaging/py.typed
.venv/lib/python3.11/site-packages/pip/py.typed
.venv/lib/python3.11/site-packages/platformdirs/py.typed
.venv/lib/python3.11/site-packages/pydantic/py.typed
.venv/lib/python3.11/site-packages/pytest/py.typed
.venv/lib/python3.11/site-packages/rich/py.typed
.venv/lib/python3.11/site-packages/semver/py.typed
.venv/lib/python3.11/site-packages/syrupy/py.typed
.venv/lib/python3.11/site-packages/tomlkit/py.typed
.venv/lib/python3.11/site-packages/typer/py.typed
gpt_hero_core/__init__.py
gpt_hero_core/heros/__init__.py
gpt_hero_core/heros/base.py
gpt_hero_core/heros/biography.py
gpt_hero_core/heros/chest.py
gpt_hero_core/heros/manager.py
gpt_hero_core/heros/mission.py
gpt_hero_core/heros/notebook.py
gpt_hero_core/heros/schema.py
gpt_hero_core/main.py
gpt_hero_core/plugins/__init__.py
gpt_hero_core/plugins/base.py
gpt_hero_core/plugins/manager.py
gpt_hero_core/skills/__init__.py
gpt_hero_core/skills/base.py
gpt_hero_core/skills/manager.py
gpt_hero_core-0.0.4.dist-info/LICENSE
gpt_hero_core-0.0.4.dist-info/METADATA
gpt_hero_core-0.0.4.dist-info/WHEEL
gpt_hero_core-0.0.4.dist-info/entry_points.txt
gpt_hero_core-0.0.4.dist-info/RECORD
