Metadata-Version: 2.1
Name: gpt-hero-core
Version: 0.0.4
Summary: A Multi-Agent System for Auto-GPT-like Task Completion
License: MIT
Author: lucemia
Author-email: lucemia@gmail.com
Requires-Python: >=3.10,<4.0
Classifier: License :: OSI Approved :: MIT License
Classifier: Programming Language :: Python :: 3
Classifier: Programming Language :: Python :: 3.10
Classifier: Programming Language :: Python :: 3.11
Requires-Dist: stevedore (>=5.0.0,<6.0.0)
